pitop/robotics/__init__.py
pitop/robotics/blockpi_rover.py
pitop/robotics/configurations.py
pitop/robotics/drive_controller.py
pitop/robotics/pan_tilt_controller.py
pitop/robotics/pan_tilt_object_tracker.py
pitop/robotics/pincer_controller.py
pitop/robotics/tilt_roll_head_controller.py
pitop/robotics/two_servo_assembly_calibrator.py
pitop/robotics/filterpy/LICENSE.md
pitop/robotics/filterpy/__init__.py
pitop/robotics/filterpy/common.py
pitop/robotics/filterpy/kalman.py
pitop/robotics/filterpy/stats.py
pitop/robotics/json/__init__.py
pitop/robotics/json/alex.json
pitop/robotics/json/bobbie.json
pitop/robotics/navigation/__init__.py
pitop/robotics/navigation/navigation_controller.py
pitop/robotics/navigation/navigator.py
pitop/robotics/navigation/core/__init__.py
pitop/robotics/navigation/core/driving_manager.py
pitop/robotics/navigation/core/goal_criteria.py
pitop/robotics/navigation/core/measurement_scheduler.py
pitop/robotics/navigation/core/robot_state.py
pitop/robotics/navigation/core/utils.py
pitop/robotics/simple_pid/LICENSE.md
pitop/robotics/simple_pid/PID.py
pitop/robotics/simple_pid/PID.pyi
pitop/robotics/simple_pid/README.md
pitop/robotics/simple_pid/__init__.py
pitop/robotics/simple_pid/py.typed
pitop.robotics-0.34.3.post1.dist-info/METADATA
pitop.robotics-0.34.3.post1.dist-info/WHEEL
pitop.robotics-0.34.3.post1.dist-info/top_level.txt
pitop.robotics-0.34.3.post1.dist-info/RECORD
